SchinkenDB/SchinkenDB.py
SchinkenDB/__init__.py
SchinkenDB/__main__.py
SchinkenDB-1.0.0.dist-info/LICENSE
SchinkenDB-1.0.0.dist-info/METADATA
SchinkenDB-1.0.0.dist-info/WHEEL
SchinkenDB-1.0.0.dist-info/top_level.txt
SchinkenDB-1.0.0.dist-info/RECORD
