Metadata-Version: 2.1
Name: SchinkenDB
Version: 1.0.0
Summary: This is my Database it is no gud and shouldn't be used lmao
Home-page: UNKNOWN
Author: DerSchinken
License: UNKNOWN
Project-URL: Source, https://github.com/DerSchinken/SchinkenDB
Platform: UNKNOWN
Classifier: Intended Audience :: Developers
Classifier: Operating System :: OS Independent
Classifier: Programming Language :: Python :: 3.6
Classifier: Programming Language :: Python :: 3.7
Classifier: Programming Language :: Python :: 3.8
Classifier: Programming Language :: Python :: 3.9
Classifier: Programming Language :: Python :: 3.10
Requires-Python: >=3.6
License-File: LICENSE
Requires-Dist: Flask (~=2.0.2)
Requires-Dist: requests (~=2.26.0)
Requires-Dist: Werkzeug (~=2.0.2)
Requires-Dist: waitress (~=2.0.0)
Requires-Dist: Paste (~=3.5.0)
Requires-Dist: BetterString (~=2.17.3)
